moadian/__init__.py
moadian/encryption.py
moadian/http.py
moadian/main.py
moadian/normalizer.py
moadian/packet.py
moadian/utils.py
moadian/verhoeff.py
moadian/xor.py
moadian-1.0.4.dist-info/LICENSE
moadian-1.0.4.dist-info/METADATA
moadian-1.0.4.dist-info/WHEEL
moadian-1.0.4.dist-info/top_level.txt
moadian-1.0.4.dist-info/RECORD
