Metadata-Version: 2.1
Name: moadian
Version: 1.0.4
Summary: Connect to Moadian API
Author-email: Mojtaba Karimi <hi@thisiskarimi.com>
License: GNU GENERAL PUBLIC LICENSE
Project-URL: Homepage, https://github.com/thisiskarimi/moadian
Keywords: moadian
Classifier: License :: OSI Approved :: MIT License
Classifier: Programming Language :: Python
Classifier: Programming Language :: Python :: 3
Requires-Python: >=3.6
License-File: LICENSE
Requires-Dist: requests
Requires-Dist: pycryptodome
